video_encoder/__init__.py
video_encoder/main.py
video_encoder-0.4.1.dist-info/METADATA
video_encoder-0.4.1.dist-info/WHEEL
video_encoder-0.4.1.dist-info/entry_points.txt
video_encoder-0.4.1.dist-info/RECORD
